MappPPy
