Metadata-Version: 2.1
Name: MappPPy
Version: 0.1.1
Summary: A basic mapping package
Home-page: https://github.com/KilroyWasHere-cs-j/MapPy.git
Author: Gabriel Tower
Author-email: <gmtower1@gmail.com>
Keywords: python,mapping,folium
